tree_sitter_sql/__init__.py
tree_sitter_sql/__init__.pyi
tree_sitter_sql/_binding.pyd
tree_sitter_sql/binding.c
tree_sitter_sql/py.typed
tree_sitter_sql/queries/highlights.scm
tree_sitter_sql/queries/indents.scm
tree_sitter_sql-0.3.11.dist-info/licenses/LICENSE
tree_sitter_sql-0.3.11.dist-info/METADATA
tree_sitter_sql-0.3.11.dist-info/WHEEL
tree_sitter_sql-0.3.11.dist-info/top_level.txt
tree_sitter_sql-0.3.11.dist-info/RECORD
