Metadata-Version: 2.4
Name: tree-sitter-sql
Version: 0.3.11
Summary: Tree-sitter Grammar for SQL
Author: derek stride
License: MIT
Project-URL: Homepage, https://github.com/derekstride/tree-sitter-sql.git
Keywords: incremental,parsing,tree-sitter,sql
Classifier: Intended Audience :: Developers
Classifier: License :: OSI Approved :: MIT License
Classifier: Topic :: Software Development :: Compilers
Classifier: Topic :: Text Processing :: Linguistic
Classifier: Typing :: Typed
Requires-Python: >=3.10
License-File: LICENSE
Provides-Extra: core
Requires-Dist: tree-sitter~=0.24; extra == "core"
Dynamic: license-file
